[
  {
    "id_match":"4000",
    "match_number":1,
    "stage":"Group Matches",
    "group":"Group A",
    "date_utc":"1998-06-10",
    "match_status":0,
    "result_type":1,
    "home_team":"BRA",
    "away_team":"SCO",
    "home_name":"Brazil",
    "away_name":"Scotland",
    "home_score":2,
    "away_score":1,
    "home_penalties":null,
    "away_penalties":null,
    "winner":"BRA",
    "home_tactics":null,
    "away_tactics":null,
    "home_possession":null,
    "away_possession":null,
    "attendance":null,
    "stadium":"Stade de France",
    "humidity":null,
    "temperature":null,
    "wind_speed":null,
    "weather":null
  },
  {
    "id_match":"8725",
    "match_number":2,
    "stage":"Group Matches",
    "group":"Group A",
    "date_utc":"1998-06-10",
    "match_status":0,
    "result_type":1,
    "home_team":"MAR",
    "away_team":"NOR",
    "home_name":"Morocco",
    "away_name":"Norway",
    "home_score":2,
    "away_score":2,
    "home_penalties":null,
    "away_penalties":null,
    "winner":null,
    "home_tactics":null,
    "away_tactics":null,
    "home_possession":null,
    "away_possession":null,
    "attendance":null,
    "stadium":"Stade de la Mosson",
    "humidity":null,
    "temperature":null,
    "wind_speed":null,
    "weather":null
  },
  {
    "id_match":"8726",
    "match_number":4,
    "stage":"Group Matches",
    "group":"Group B",
    "date_utc":"1998-06-11",
    "match_status":0,
    "result_type":1,
    "home_team":"ITA",
    "away_team":"CHI",
    "home_name":"Italy",
    "away_name":"Chile",
    "home_score":2,
    "away_score":2,
    "home_penalties":null,
    "away_penalties":null,
    "winner":null,
    "home_tactics":null,
    "away_tactics":null,
    "home_possession":null,
    "away_possession":null,
    "attendance":null,
    "stadium":"Stade de Bordeaux",
    "humidity":null,
    "temperature":null,
    "wind_speed":null,
    "weather":null
  },
  {
    "id_match":"8727",
    "match_number":3,
    "stage":"Group Matches",
    "group":"Group B",
    "date_utc":"1998-06-11",
    "match_status":0,
    "result_type":1,
    "home_team":"CMR",
    "away_team":"AUT",
    "home_name":"Cameroon",
    "away_name":"Austria",
    "home_score":1,
    "away_score":1,
    "home_penalties":null,
    "away_penalties":null,
    "winner":null,
    "home_tactics":null,
    "away_tactics":null,
    "home_possession":null,
    "away_possession":null,
    "attendance":null,
    "stadium":"Stade de Toulouse",
    "humidity":null,
    "temperature":null,
    "wind_speed":null,
    "weather":null
  },
  {
    "id_match":"8728",
    "match_number":7,
    "stage":"Group Matches",
    "group":"Group D",
    "date_utc":"1998-06-12",
    "match_status":0,
    "result_type":1,
    "home_team":"PAR",
    "away_team":"BUL",
    "home_name":"Paraguay",
    "away_name":"Bulgaria",
    "home_score":0,
    "away_score":0,
    "home_penalties":null,
    "away_penalties":null,
    "winner":null,
    "home_tactics":null,
    "away_tactics":null,
    "home_possession":null,
    "away_possession":null,
    "attendance":null,
    "stadium":"Stade de la Mosson",
    "humidity":null,
    "temperature":null,
    "wind_speed":null,
    "weather":null
  },
  {
    "id_match":"8729",
    "match_number":5,
    "stage":"Group Matches",
    "group":"Group C",
    "date_utc":"1998-06-12",
    "match_status":0,
    "result_type":1,
    "home_team":"KSA",
    "away_team":"DEN",
    "home_name":"Saudi Arabia",
    "away_name":"Denmark",
    "home_score":0,
    "away_score":1,
    "home_penalties":null,
    "away_penalties":null,
    "winner":"DEN",
    "home_tactics":null,
    "away_tactics":null,
    "home_possession":null,
    "away_possession":null,
    "attendance":null,
    "stadium":"Stade Felix Bollaert",
    "humidity":null,
    "temperature":null,
    "wind_speed":null,
    "weather":null
  },
  {
    "id_match":"8730",
    "match_number":6,
    "stage":"Group Matches",
    "group":"Group C",
    "date_utc":"1998-06-12",
    "match_status":0,
    "result_type":1,
    "home_team":"FRA",
    "away_team":"RSA",
    "home_name":"France",
    "away_name":"South Africa",
    "home_score":3,
    "away_score":0,
    "home_penalties":null,
    "away_penalties":null,
    "winner":"FRA",
    "home_tactics":null,
    "away_tactics":null,
    "home_possession":null,
    "away_possession":null,
    "attendance":null,
    "stadium":"Stade Vélodrome",
    "humidity":null,
    "temperature":null,
    "wind_speed":null,
    "weather":null
  },
  {
    "id_match":"8731",
    "match_number":10,
    "stage":"Group Matches",
    "group":"Group D",
    "date_utc":"1998-06-13",
    "match_status":0,
    "result_type":1,
    "home_team":"ESP",
    "away_team":"NGA",
    "home_name":"Spain",
    "away_name":"Nigeria",
    "home_score":2,
    "away_score":3,
    "home_penalties":null,
    "away_penalties":null,
    "winner":"NGA",
    "home_tactics":null,
    "away_tactics":null,
    "home_possession":null,
    "away_possession":null,
    "attendance":null,
    "stadium":"Stade de la Beaujoire",
    "humidity":null,
    "temperature":null,
    "wind_speed":null,
    "weather":null
  },
  {
    "id_match":"8732",
    "match_number":9,
    "stage":"Group Matches",
    "group":"Group E",
    "date_utc":"1998-06-13",
    "match_status":0,
    "result_type":1,
    "home_team":"KOR",
    "away_team":"MEX",
    "home_name":"Korea Republic",
    "away_name":"Mexico",
    "home_score":1,
    "away_score":3,
    "home_penalties":null,
    "away_penalties":null,
    "winner":"MEX",
    "home_tactics":null,
    "away_tactics":null,
    "home_possession":null,
    "away_possession":null,
    "attendance":null,
    "stadium":"Stade de Gerland",
    "humidity":null,
    "temperature":null,
    "wind_speed":null,
    "weather":null
  },
  {
    "id_match":"8733",
    "match_number":8,
    "stage":"Group Matches",
    "group":"Group E",
    "date_utc":"1998-06-13",
    "match_status":0,
    "result_type":1,
    "home_team":"NED",
    "away_team":"BEL",
    "home_name":"Netherlands",
    "away_name":"Belgium",
    "home_score":0,
    "away_score":0,
    "home_penalties":null,
    "away_penalties":null,
    "winner":null,
    "home_tactics":null,
    "away_tactics":null,
    "home_possession":null,
    "away_possession":null,
    "attendance":null,
    "stadium":"Stade de France",
    "humidity":null,
    "temperature":null,
    "wind_speed":null,
    "weather":null
  },
  {
    "id_match":"8734",
    "match_number":13,
    "stage":"Group Matches",
    "group":"Group H",
    "date_utc":"1998-06-14",
    "match_status":0,
    "result_type":1,
    "home_team":"ARG",
    "away_team":"JPN",
    "home_name":"Argentina",
    "away_name":"Japan",
    "home_score":1,
    "away_score":0,
    "home_penalties":null,
    "away_penalties":null,
    "winner":"ARG",
    "home_tactics":null,
    "away_tactics":null,
    "home_possession":null,
    "away_possession":null,
    "attendance":null,
    "stadium":"Stade de Toulouse",
    "humidity":null,
    "temperature":null,
    "wind_speed":null,
    "weather":null
  },
  {
    "id_match":"8735",
    "match_number":12,
    "stage":"Group Matches",
    "group":"Group F",
    "date_utc":"1998-06-14",
    "match_status":0,
    "result_type":1,
    "home_team":"YUG",
    "away_team":"IRN",
    "home_name":"Yugoslavia",
    "away_name":"IR Iran",
    "home_score":1,
    "away_score":0,
    "home_penalties":null,
    "away_penalties":null,
    "winner":"YUG",
    "home_tactics":null,
    "away_tactics":null,
    "home_possession":null,
    "away_possession":null,
    "attendance":null,
    "stadium":"Stade Geoffroy Guichard",
    "humidity":null,
    "temperature":null,
    "wind_speed":null,
    "weather":null
  },
  {
    "id_match":"8736",
    "match_number":11,
    "stage":"Group Matches",
    "group":"Group H",
    "date_utc":"1998-06-14",
    "match_status":0,
    "result_type":1,
    "home_team":"JAM",
    "away_team":"CRO",
    "home_name":"Jamaica",
    "away_name":"Croatia",
    "home_score":1,
    "away_score":3,
    "home_penalties":null,
    "away_penalties":null,
    "winner":"CRO",
    "home_tactics":null,
    "away_tactics":null,
    "home_possession":null,
    "away_possession":null,
    "attendance":null,
    "stadium":"Stade Felix Bollaert",
    "humidity":null,
    "temperature":null,
    "wind_speed":null,
    "weather":null
  },
  {
    "id_match":"8738",
    "match_number":14,
    "stage":"Group Matches",
    "group":"Group F",
    "date_utc":"1998-06-15",
    "match_status":0,
    "result_type":1,
    "home_team":"GER",
    "away_team":"USA",
    "home_name":"Germany",
    "away_name":"USA",
    "home_score":2,
    "away_score":0,
    "home_penalties":null,
    "away_penalties":null,
    "winner":"GER",
    "home_tactics":null,
    "away_tactics":null,
    "home_possession":null,
    "away_possession":null,
    "attendance":null,
    "stadium":"Parc des Princes",
    "humidity":null,
    "temperature":null,
    "wind_speed":null,
    "weather":null
  },
  {
    "id_match":"8739",
    "match_number":15,
    "stage":"Group Matches",
    "group":"Group G",
    "date_utc":"1998-06-15",
    "match_status":0,
    "result_type":1,
    "home_team":"ROU",
    "away_team":"COL",
    "home_name":"Romania",
    "away_name":"Colombia",
    "home_score":1,
    "away_score":0,
    "home_penalties":null,
    "away_penalties":null,
    "winner":"ROU",
    "home_tactics":null,
    "away_tactics":null,
    "home_possession":null,
    "away_possession":null,
    "attendance":null,
    "stadium":"Stade de Gerland",
    "humidity":null,
    "temperature":null,
    "wind_speed":null,
    "weather":null
  },
  {
    "id_match":"8740",
    "match_number":16,
    "stage":"Group Matches",
    "group":"Group G",
    "date_utc":"1998-06-15",
    "match_status":0,
    "result_type":1,
    "home_team":"ENG",
    "away_team":"TUN",
    "home_name":"England",
    "away_name":"Tunisia",
    "home_score":2,
    "away_score":0,
    "home_penalties":null,
    "away_penalties":null,
    "winner":"ENG",
    "home_tactics":null,
    "away_tactics":null,
    "home_possession":null,
    "away_possession":null,
    "attendance":null,
    "stadium":"Stade Vélodrome",
    "humidity":null,
    "temperature":null,
    "wind_speed":null,
    "weather":null
  },
  {
    "id_match":"8741",
    "match_number":17,
    "stage":"Group Matches",
    "group":"Group A",
    "date_utc":"1998-06-16",
    "match_status":0,
    "result_type":1,
    "home_team":"SCO",
    "away_team":"NOR",
    "home_name":"Scotland",
    "away_name":"Norway",
    "home_score":1,
    "away_score":1,
    "home_penalties":null,
    "away_penalties":null,
    "winner":null,
    "home_tactics":null,
    "away_tactics":null,
    "home_possession":null,
    "away_possession":null,
    "attendance":null,
    "stadium":"Stade de Bordeaux",
    "humidity":null,
    "temperature":null,
    "wind_speed":null,
    "weather":null
  },
  {
    "id_match":"8742",
    "match_number":18,
    "stage":"Group Matches",
    "group":"Group A",
    "date_utc":"1998-06-16",
    "match_status":0,
    "result_type":1,
    "home_team":"BRA",
    "away_team":"MAR",
    "home_name":"Brazil",
    "away_name":"Morocco",
    "home_score":3,
    "away_score":0,
    "home_penalties":null,
    "away_penalties":null,
    "winner":"BRA",
    "home_tactics":null,
    "away_tactics":null,
    "home_possession":null,
    "away_possession":null,
    "attendance":null,
    "stadium":"Stade de la Beaujoire",
    "humidity":null,
    "temperature":null,
    "wind_speed":null,
    "weather":null
  },
  {
    "id_match":"8743",
    "match_number":19,
    "stage":"Group Matches",
    "group":"Group B",
    "date_utc":"1998-06-17",
    "match_status":0,
    "result_type":1,
    "home_team":"CHI",
    "away_team":"AUT",
    "home_name":"Chile",
    "away_name":"Austria",
    "home_score":1,
    "away_score":1,
    "home_penalties":null,
    "away_penalties":null,
    "winner":null,
    "home_tactics":null,
    "away_tactics":null,
    "home_possession":null,
    "away_possession":null,
    "attendance":null,
    "stadium":"Stade Geoffroy Guichard",
    "humidity":null,
    "temperature":null,
    "wind_speed":null,
    "weather":null
  },
  {
    "id_match":"8744",
    "match_number":20,
    "stage":"Group Matches",
    "group":"Group B",
    "date_utc":"1998-06-17",
    "match_status":0,
    "result_type":1,
    "home_team":"ITA",
    "away_team":"CMR",
    "home_name":"Italy",
    "away_name":"Cameroon",
    "home_score":3,
    "away_score":0,
    "home_penalties":null,
    "away_penalties":null,
    "winner":"ITA",
    "home_tactics":null,
    "away_tactics":null,
    "home_possession":null,
    "away_possession":null,
    "attendance":null,
    "stadium":"Stade de la Mosson",
    "humidity":null,
    "temperature":null,
    "wind_speed":null,
    "weather":null
  },
  {
    "id_match":"8746",
    "match_number":22,
    "stage":"Group Matches",
    "group":"Group C",
    "date_utc":"1998-06-18",
    "match_status":0,
    "result_type":1,
    "home_team":"RSA",
    "away_team":"DEN",
    "home_name":"South Africa",
    "away_name":"Denmark",
    "home_score":1,
    "away_score":1,
    "home_penalties":null,
    "away_penalties":null,
    "winner":null,
    "home_tactics":null,
    "away_tactics":null,
    "home_possession":null,
    "away_possession":null,
    "attendance":null,
    "stadium":"Stade de Toulouse",
    "humidity":null,
    "temperature":null,
    "wind_speed":null,
    "weather":null
  },
  {
    "id_match":"8745",
    "match_number":21,
    "stage":"Group Matches",
    "group":"Group C",
    "date_utc":"1998-06-18",
    "match_status":0,
    "result_type":1,
    "home_team":"FRA",
    "away_team":"KSA",
    "home_name":"France",
    "away_name":"Saudi Arabia",
    "home_score":4,
    "away_score":0,
    "home_penalties":null,
    "away_penalties":null,
    "winner":"FRA",
    "home_tactics":null,
    "away_tactics":null,
    "home_possession":null,
    "away_possession":null,
    "attendance":null,
    "stadium":"Stade de France",
    "humidity":null,
    "temperature":null,
    "wind_speed":null,
    "weather":null
  },
  {
    "id_match":"8747",
    "match_number":23,
    "stage":"Group Matches",
    "group":"Group D",
    "date_utc":"1998-06-19",
    "match_status":0,
    "result_type":1,
    "home_team":"NGA",
    "away_team":"BUL",
    "home_name":"Nigeria",
    "away_name":"Bulgaria",
    "home_score":1,
    "away_score":0,
    "home_penalties":null,
    "away_penalties":null,
    "winner":"NGA",
    "home_tactics":null,
    "away_tactics":null,
    "home_possession":null,
    "away_possession":null,
    "attendance":null,
    "stadium":"Parc des Princes",
    "humidity":null,
    "temperature":null,
    "wind_speed":null,
    "weather":null
  },
  {
    "id_match":"8748",
    "match_number":24,
    "stage":"Group Matches",
    "group":"Group D",
    "date_utc":"1998-06-19",
    "match_status":0,
    "result_type":1,
    "home_team":"ESP",
    "away_team":"PAR",
    "home_name":"Spain",
    "away_name":"Paraguay",
    "home_score":0,
    "away_score":0,
    "home_penalties":null,
    "away_penalties":null,
    "winner":null,
    "home_tactics":null,
    "away_tactics":null,
    "home_possession":null,
    "away_possession":null,
    "attendance":null,
    "stadium":"Stade Geoffroy Guichard",
    "humidity":null,
    "temperature":null,
    "wind_speed":null,
    "weather":null
  },
  {
    "id_match":"8751",
    "match_number":27,
    "stage":"Group Matches",
    "group":"Group H",
    "date_utc":"1998-06-20",
    "match_status":0,
    "result_type":1,
    "home_team":"JPN",
    "away_team":"CRO",
    "home_name":"Japan",
    "away_name":"Croatia",
    "home_score":0,
    "away_score":1,
    "home_penalties":null,
    "away_penalties":null,
    "winner":"CRO",
    "home_tactics":null,
    "away_tactics":null,
    "home_possession":null,
    "away_possession":null,
    "attendance":null,
    "stadium":"Stade de la Beaujoire",
    "humidity":null,
    "temperature":null,
    "wind_speed":null,
    "weather":null
  },
  {
    "id_match":"8750",
    "match_number":26,
    "stage":"Group Matches",
    "group":"Group E",
    "date_utc":"1998-06-20",
    "match_status":0,
    "result_type":1,
    "home_team":"BEL",
    "away_team":"MEX",
    "home_name":"Belgium",
    "away_name":"Mexico",
    "home_score":2,
    "away_score":2,
    "home_penalties":null,
    "away_penalties":null,
    "winner":null,
    "home_tactics":null,
    "away_tactics":null,
    "home_possession":null,
    "away_possession":null,
    "attendance":null,
    "stadium":"Stade de Bordeaux",
    "humidity":null,
    "temperature":null,
    "wind_speed":null,
    "weather":null
  },
  {
    "id_match":"8749",
    "match_number":25,
    "stage":"Group Matches",
    "group":"Group E",
    "date_utc":"1998-06-20",
    "match_status":0,
    "result_type":1,
    "home_team":"NED",
    "away_team":"KOR",
    "home_name":"Netherlands",
    "away_name":"Korea Republic",
    "home_score":5,
    "away_score":0,
    "home_penalties":null,
    "away_penalties":null,
    "winner":"NED",
    "home_tactics":null,
    "away_tactics":null,
    "home_possession":null,
    "away_possession":null,
    "attendance":null,
    "stadium":"Stade Vélodrome",
    "humidity":null,
    "temperature":null,
    "wind_speed":null,
    "weather":null
  },
  {
    "id_match":"8753",
    "match_number":29,
    "stage":"Group Matches",
    "group":"Group F",
    "date_utc":"1998-06-21",
    "match_status":0,
    "result_type":1,
    "home_team":"GER",
    "away_team":"YUG",
    "home_name":"Germany",
    "away_name":"Yugoslavia",
    "home_score":2,
    "away_score":2,
    "home_penalties":null,
    "away_penalties":null,
    "winner":null,
    "home_tactics":null,
    "away_tactics":null,
    "home_possession":null,
    "away_possession":null,
    "attendance":null,
    "stadium":"Stade Felix Bollaert",
    "humidity":null,
    "temperature":null,
    "wind_speed":null,
    "weather":null
  },
  {
    "id_match":"8752",
    "match_number":28,
    "stage":"Group Matches",
    "group":"Group H",
    "date_utc":"1998-06-21",
    "match_status":0,
    "result_type":1,
    "home_team":"ARG",
    "away_team":"JAM",
    "home_name":"Argentina",
    "away_name":"Jamaica",
    "home_score":5,
    "away_score":0,
    "home_penalties":null,
    "away_penalties":null,
    "winner":"ARG",
    "home_tactics":null,
    "away_tactics":null,
    "home_possession":null,
    "away_possession":null,
    "attendance":null,
    "stadium":"Parc des Princes",
    "humidity":null,
    "temperature":null,
    "wind_speed":null,
    "weather":null
  },
  {
    "id_match":"8754",
    "match_number":30,
    "stage":"Group Matches",
    "group":"Group F",
    "date_utc":"1998-06-21",
    "match_status":0,
    "result_type":1,
    "home_team":"USA",
    "away_team":"IRN",
    "home_name":"USA",
    "away_name":"IR Iran",
    "home_score":1,
    "away_score":2,
    "home_penalties":null,
    "away_penalties":null,
    "winner":"IRN",
    "home_tactics":null,
    "away_tactics":null,
    "home_possession":null,
    "away_possession":null,
    "attendance":null,
    "stadium":"Stade de Gerland",
    "humidity":null,
    "temperature":null,
    "wind_speed":null,
    "weather":null
  },
  {
    "id_match":"8756",
    "match_number":32,
    "stage":"Group Matches",
    "group":"Group G",
    "date_utc":"1998-06-22",
    "match_status":0,
    "result_type":1,
    "home_team":"ROU",
    "away_team":"ENG",
    "home_name":"Romania",
    "away_name":"England",
    "home_score":2,
    "away_score":1,
    "home_penalties":null,
    "away_penalties":null,
    "winner":"ROU",
    "home_tactics":null,
    "away_tactics":null,
    "home_possession":null,
    "away_possession":null,
    "attendance":null,
    "stadium":"Stade de Toulouse",
    "humidity":null,
    "temperature":null,
    "wind_speed":null,
    "weather":null
  },
  {
    "id_match":"8755",
    "match_number":31,
    "stage":"Group Matches",
    "group":"Group G",
    "date_utc":"1998-06-22",
    "match_status":0,
    "result_type":1,
    "home_team":"COL",
    "away_team":"TUN",
    "home_name":"Colombia",
    "away_name":"Tunisia",
    "home_score":1,
    "away_score":0,
    "home_penalties":null,
    "away_penalties":null,
    "winner":"COL",
    "home_tactics":null,
    "away_tactics":null,
    "home_possession":null,
    "away_possession":null,
    "attendance":null,
    "stadium":"Stade de la Mosson",
    "humidity":null,
    "temperature":null,
    "wind_speed":null,
    "weather":null
  },
  {
    "id_match":"8760",
    "match_number":36,
    "stage":"Group Matches",
    "group":"Group B",
    "date_utc":"1998-06-23",
    "match_status":0,
    "result_type":1,
    "home_team":"CHI",
    "away_team":"CMR",
    "home_name":"Chile",
    "away_name":"Cameroon",
    "home_score":1,
    "away_score":1,
    "home_penalties":null,
    "away_penalties":null,
    "winner":null,
    "home_tactics":null,
    "away_tactics":null,
    "home_possession":null,
    "away_possession":null,
    "attendance":null,
    "stadium":"Stade de la Beaujoire",
    "humidity":null,
    "temperature":null,
    "wind_speed":null,
    "weather":null
  },
  {
    "id_match":"8757",
    "match_number":33,
    "stage":"Group Matches",
    "group":"Group B",
    "date_utc":"1998-06-23",
    "match_status":0,
    "result_type":1,
    "home_team":"ITA",
    "away_team":"AUT",
    "home_name":"Italy",
    "away_name":"Austria",
    "home_score":2,
    "away_score":1,
    "home_penalties":null,
    "away_penalties":null,
    "winner":"ITA",
    "home_tactics":null,
    "away_tactics":null,
    "home_possession":null,
    "away_possession":null,
    "attendance":null,
    "stadium":"Stade de France",
    "humidity":null,
    "temperature":null,
    "wind_speed":null,
    "weather":null
  },
  {
    "id_match":"8759",
    "match_number":35,
    "stage":"Group Matches",
    "group":"Group A",
    "date_utc":"1998-06-23",
    "match_status":0,
    "result_type":1,
    "home_team":"BRA",
    "away_team":"NOR",
    "home_name":"Brazil",
    "away_name":"Norway",
    "home_score":1,
    "away_score":2,
    "home_penalties":null,
    "away_penalties":null,
    "winner":"NOR",
    "home_tactics":null,
    "away_tactics":null,
    "home_possession":null,
    "away_possession":null,
    "attendance":null,
    "stadium":"Stade Vélodrome",
    "humidity":null,
    "temperature":null,
    "wind_speed":null,
    "weather":null
  },
  {
    "id_match":"8758",
    "match_number":34,
    "stage":"Group Matches",
    "group":"Group A",
    "date_utc":"1998-06-23",
    "match_status":0,
    "result_type":1,
    "home_team":"SCO",
    "away_team":"MAR",
    "home_name":"Scotland",
    "away_name":"Morocco",
    "home_score":0,
    "away_score":3,
    "home_penalties":null,
    "away_penalties":null,
    "winner":"MAR",
    "home_tactics":null,
    "away_tactics":null,
    "home_possession":null,
    "away_possession":null,
    "attendance":null,
    "stadium":"Stade Geoffroy Guichard",
    "humidity":null,
    "temperature":null,
    "wind_speed":null,
    "weather":null
  },
  {
    "id_match":"8764",
    "match_number":40,
    "stage":"Group Matches",
    "group":"Group C",
    "date_utc":"1998-06-24",
    "match_status":0,
    "result_type":1,
    "home_team":"RSA",
    "away_team":"KSA",
    "home_name":"South Africa",
    "away_name":"Saudi Arabia",
    "home_score":2,
    "away_score":2,
    "home_penalties":null,
    "away_penalties":null,
    "winner":null,
    "home_tactics":null,
    "away_tactics":null,
    "home_possession":null,
    "away_possession":null,
    "attendance":null,
    "stadium":"Stade de Bordeaux",
    "humidity":null,
    "temperature":null,
    "wind_speed":null,
    "weather":null
  },
  {
    "id_match":"8762",
    "match_number":38,
    "stage":"Group Matches",
    "group":"Group C",
    "date_utc":"1998-06-24",
    "match_status":0,
    "result_type":1,
    "home_team":"FRA",
    "away_team":"DEN",
    "home_name":"France",
    "away_name":"Denmark",
    "home_score":2,
    "away_score":1,
    "home_penalties":null,
    "away_penalties":null,
    "winner":"FRA",
    "home_tactics":null,
    "away_tactics":null,
    "home_possession":null,
    "away_possession":null,
    "attendance":null,
    "stadium":"Stade de Gerland",
    "humidity":null,
    "temperature":null,
    "wind_speed":null,
    "weather":null
  },
  {
    "id_match":"8763",
    "match_number":39,
    "stage":"Group Matches",
    "group":"Group D",
    "date_utc":"1998-06-24",
    "match_status":0,
    "result_type":1,
    "home_team":"NGA",
    "away_team":"PAR",
    "home_name":"Nigeria",
    "away_name":"Paraguay",
    "home_score":1,
    "away_score":3,
    "home_penalties":null,
    "away_penalties":null,
    "winner":"PAR",
    "home_tactics":null,
    "away_tactics":null,
    "home_possession":null,
    "away_possession":null,
    "attendance":null,
    "stadium":"Stade de Toulouse",
    "humidity":null,
    "temperature":null,
    "wind_speed":null,
    "weather":null
  },
  {
    "id_match":"8761",
    "match_number":37,
    "stage":"Group Matches",
    "group":"Group D",
    "date_utc":"1998-06-24",
    "match_status":0,
    "result_type":1,
    "home_team":"ESP",
    "away_team":"BUL",
    "home_name":"Spain",
    "away_name":"Bulgaria",
    "home_score":6,
    "away_score":1,
    "home_penalties":null,
    "away_penalties":null,
    "winner":"ESP",
    "home_tactics":null,
    "away_tactics":null,
    "home_possession":null,
    "away_possession":null,
    "attendance":null,
    "stadium":"Stade Felix Bollaert",
    "humidity":null,
    "temperature":null,
    "wind_speed":null,
    "weather":null
  },
  {
    "id_match":"8765",
    "match_number":41,
    "stage":"Group Matches",
    "group":"Group E",
    "date_utc":"1998-06-25",
    "match_status":0,
    "result_type":1,
    "home_team":"BEL",
    "away_team":"KOR",
    "home_name":"Belgium",
    "away_name":"Korea Republic",
    "home_score":1,
    "away_score":1,
    "home_penalties":null,
    "away_penalties":null,
    "winner":null,
    "home_tactics":null,
    "away_tactics":null,
    "home_possession":null,
    "away_possession":null,
    "attendance":null,
    "stadium":"Parc des Princes",
    "humidity":null,
    "temperature":null,
    "wind_speed":null,
    "weather":null
  },
  {
    "id_match":"8766",
    "match_number":42,
    "stage":"Group Matches",
    "group":"Group E",
    "date_utc":"1998-06-25",
    "match_status":0,
    "result_type":1,
    "home_team":"NED",
    "away_team":"MEX",
    "home_name":"Netherlands",
    "away_name":"Mexico",
    "home_score":2,
    "away_score":2,
    "home_penalties":null,
    "away_penalties":null,
    "winner":null,
    "home_tactics":null,
    "away_tactics":null,
    "home_possession":null,
    "away_possession":null,
    "attendance":null,
    "stadium":"Stade Geoffroy Guichard",
    "humidity":null,
    "temperature":null,
    "wind_speed":null,
    "weather":null
  },
  {
    "id_match":"8767",
    "match_number":43,
    "stage":"Group Matches",
    "group":"Group F",
    "date_utc":"1998-06-25",
    "match_status":0,
    "result_type":1,
    "home_team":"GER",
    "away_team":"IRN",
    "home_name":"Germany",
    "away_name":"IR Iran",
    "home_score":2,
    "away_score":0,
    "home_penalties":null,
    "away_penalties":null,
    "winner":"GER",
    "home_tactics":null,
    "away_tactics":null,
    "home_possession":null,
    "away_possession":null,
    "attendance":null,
    "stadium":"Stade de la Mosson",
    "humidity":null,
    "temperature":null,
    "wind_speed":null,
    "weather":null
  },
  {
    "id_match":"8768",
    "match_number":44,
    "stage":"Group Matches",
    "group":"Group F",
    "date_utc":"1998-06-25",
    "match_status":0,
    "result_type":1,
    "home_team":"USA",
    "away_team":"YUG",
    "home_name":"USA",
    "away_name":"Yugoslavia",
    "home_score":0,
    "away_score":1,
    "home_penalties":null,
    "away_penalties":null,
    "winner":"YUG",
    "home_tactics":null,
    "away_tactics":null,
    "home_possession":null,
    "away_possession":null,
    "attendance":null,
    "stadium":"Stade de la Beaujoire",
    "humidity":null,
    "temperature":null,
    "wind_speed":null,
    "weather":null
  },
  {
    "id_match":"8769",
    "match_number":45,
    "stage":"Group Matches",
    "group":"Group G",
    "date_utc":"1998-06-26",
    "match_status":0,
    "result_type":1,
    "home_team":"ROU",
    "away_team":"TUN",
    "home_name":"Romania",
    "away_name":"Tunisia",
    "home_score":1,
    "away_score":1,
    "home_penalties":null,
    "away_penalties":null,
    "winner":null,
    "home_tactics":null,
    "away_tactics":null,
    "home_possession":null,
    "away_possession":null,
    "attendance":null,
    "stadium":"Stade de France",
    "humidity":null,
    "temperature":null,
    "wind_speed":null,
    "weather":null
  },
  {
    "id_match":"8770",
    "match_number":46,
    "stage":"Group Matches",
    "group":"Group G",
    "date_utc":"1998-06-26",
    "match_status":0,
    "result_type":1,
    "home_team":"COL",
    "away_team":"ENG",
    "home_name":"Colombia",
    "away_name":"England",
    "home_score":0,
    "away_score":2,
    "home_penalties":null,
    "away_penalties":null,
    "winner":"ENG",
    "home_tactics":null,
    "away_tactics":null,
    "home_possession":null,
    "away_possession":null,
    "attendance":null,
    "stadium":"Stade Felix Bollaert",
    "humidity":null,
    "temperature":null,
    "wind_speed":null,
    "weather":null
  },
  {
    "id_match":"8772",
    "match_number":48,
    "stage":"Group Matches",
    "group":"Group H",
    "date_utc":"1998-06-26",
    "match_status":0,
    "result_type":1,
    "home_team":"ARG",
    "away_team":"CRO",
    "home_name":"Argentina",
    "away_name":"Croatia",
    "home_score":1,
    "away_score":0,
    "home_penalties":null,
    "away_penalties":null,
    "winner":"ARG",
    "home_tactics":null,
    "away_tactics":null,
    "home_possession":null,
    "away_possession":null,
    "attendance":null,
    "stadium":"Stade de Bordeaux",
    "humidity":null,
    "temperature":null,
    "wind_speed":null,
    "weather":null
  },
  {
    "id_match":"8771",
    "match_number":47,
    "stage":"Group Matches",
    "group":"Group H",
    "date_utc":"1998-06-26",
    "match_status":0,
    "result_type":1,
    "home_team":"JPN",
    "away_team":"JAM",
    "home_name":"Japan",
    "away_name":"Jamaica",
    "home_score":1,
    "away_score":2,
    "home_penalties":null,
    "away_penalties":null,
    "winner":"JAM",
    "home_tactics":null,
    "away_tactics":null,
    "home_possession":null,
    "away_possession":null,
    "attendance":null,
    "stadium":"Stade de Gerland",
    "humidity":null,
    "temperature":null,
    "wind_speed":null,
    "weather":null
  },
  {
    "id_match":"8774",
    "match_number":50,
    "stage":"Round of 16",
    "group":null,
    "date_utc":"1998-06-27",
    "match_status":0,
    "result_type":1,
    "home_team":"ITA",
    "away_team":"NOR",
    "home_name":"Italy",
    "away_name":"Norway",
    "home_score":1,
    "away_score":0,
    "home_penalties":null,
    "away_penalties":null,
    "winner":"ITA",
    "home_tactics":null,
    "away_tactics":null,
    "home_possession":null,
    "away_possession":null,
    "attendance":null,
    "stadium":"Stade Vélodrome",
    "humidity":null,
    "temperature":null,
    "wind_speed":null,
    "weather":null
  },
  {
    "id_match":"8773",
    "match_number":49,
    "stage":"Round of 16",
    "group":null,
    "date_utc":"1998-06-27",
    "match_status":0,
    "result_type":1,
    "home_team":"BRA",
    "away_team":"CHI",
    "home_name":"Brazil",
    "away_name":"Chile",
    "home_score":4,
    "away_score":1,
    "home_penalties":null,
    "away_penalties":null,
    "winner":"BRA",
    "home_tactics":null,
    "away_tactics":null,
    "home_possession":null,
    "away_possession":null,
    "attendance":null,
    "stadium":"Parc des Princes",
    "humidity":null,
    "temperature":null,
    "wind_speed":null,
    "weather":null
  },
  {
    "id_match":"8776",
    "match_number":52,
    "stage":"Round of 16",
    "group":null,
    "date_utc":"1998-06-28",
    "match_status":0,
    "result_type":8,
    "home_team":"FRA",
    "away_team":"PAR",
    "home_name":"France",
    "away_name":"Paraguay",
    "home_score":1,
    "away_score":0,
    "home_penalties":null,
    "away_penalties":null,
    "winner":"FRA",
    "home_tactics":null,
    "away_tactics":null,
    "home_possession":null,
    "away_possession":null,
    "attendance":null,
    "stadium":"Stade Felix Bollaert",
    "humidity":null,
    "temperature":null,
    "wind_speed":null,
    "weather":null
  },
  {
    "id_match":"8775",
    "match_number":51,
    "stage":"Round of 16",
    "group":null,
    "date_utc":"1998-06-28",
    "match_status":0,
    "result_type":1,
    "home_team":"NGA",
    "away_team":"DEN",
    "home_name":"Nigeria",
    "away_name":"Denmark",
    "home_score":1,
    "away_score":4,
    "home_penalties":null,
    "away_penalties":null,
    "winner":"DEN",
    "home_tactics":null,
    "away_tactics":null,
    "home_possession":null,
    "away_possession":null,
    "attendance":null,
    "stadium":"Stade de France",
    "humidity":null,
    "temperature":null,
    "wind_speed":null,
    "weather":null
  },
  {
    "id_match":"8777",
    "match_number":53,
    "stage":"Round of 16",
    "group":null,
    "date_utc":"1998-06-29",
    "match_status":0,
    "result_type":1,
    "home_team":"GER",
    "away_team":"MEX",
    "home_name":"Germany",
    "away_name":"Mexico",
    "home_score":2,
    "away_score":1,
    "home_penalties":null,
    "away_penalties":null,
    "winner":"GER",
    "home_tactics":null,
    "away_tactics":null,
    "home_possession":null,
    "away_possession":null,
    "attendance":null,
    "stadium":"Stade de la Mosson",
    "humidity":null,
    "temperature":null,
    "wind_speed":null,
    "weather":null
  },
  {
    "id_match":"8778",
    "match_number":54,
    "stage":"Round of 16",
    "group":null,
    "date_utc":"1998-06-29",
    "match_status":0,
    "result_type":1,
    "home_team":"NED",
    "away_team":"YUG",
    "home_name":"Netherlands",
    "away_name":"Yugoslavia",
    "home_score":2,
    "away_score":1,
    "home_penalties":null,
    "away_penalties":null,
    "winner":"NED",
    "home_tactics":null,
    "away_tactics":null,
    "home_possession":null,
    "away_possession":null,
    "attendance":null,
    "stadium":"Stade de Toulouse",
    "humidity":null,
    "temperature":null,
    "wind_speed":null,
    "weather":null
  },
  {
    "id_match":"8780",
    "match_number":56,
    "stage":"Round of 16",
    "group":null,
    "date_utc":"1998-06-30",
    "match_status":0,
    "result_type":1,
    "home_team":"ROU",
    "away_team":"CRO",
    "home_name":"Romania",
    "away_name":"Croatia",
    "home_score":0,
    "away_score":1,
    "home_penalties":null,
    "away_penalties":null,
    "winner":"CRO",
    "home_tactics":null,
    "away_tactics":null,
    "home_possession":null,
    "away_possession":null,
    "attendance":null,
    "stadium":"Stade de Bordeaux",
    "humidity":null,
    "temperature":null,
    "wind_speed":null,
    "weather":null
  },
  {
    "id_match":"8779",
    "match_number":55,
    "stage":"Round of 16",
    "group":null,
    "date_utc":"1998-06-30",
    "match_status":0,
    "result_type":2,
    "home_team":"ARG",
    "away_team":"ENG",
    "home_name":"Argentina",
    "away_name":"England",
    "home_score":2,
    "away_score":2,
    "home_penalties":4.0,
    "away_penalties":3.0,
    "winner":"ARG",
    "home_tactics":null,
    "away_tactics":null,
    "home_possession":null,
    "away_possession":null,
    "attendance":null,
    "stadium":"Stade Geoffroy Guichard",
    "humidity":null,
    "temperature":null,
    "wind_speed":null,
    "weather":null
  },
  {
    "id_match":"8781",
    "match_number":57,
    "stage":"Quarter-final",
    "group":null,
    "date_utc":"1998-07-03",
    "match_status":0,
    "result_type":2,
    "home_team":"ITA",
    "away_team":"FRA",
    "home_name":"Italy",
    "away_name":"France",
    "home_score":0,
    "away_score":0,
    "home_penalties":3.0,
    "away_penalties":4.0,
    "winner":"FRA",
    "home_tactics":null,
    "away_tactics":null,
    "home_possession":null,
    "away_possession":null,
    "attendance":null,
    "stadium":"Stade de France",
    "humidity":null,
    "temperature":null,
    "wind_speed":null,
    "weather":null
  },
  {
    "id_match":"8782",
    "match_number":58,
    "stage":"Quarter-final",
    "group":null,
    "date_utc":"1998-07-03",
    "match_status":0,
    "result_type":1,
    "home_team":"BRA",
    "away_team":"DEN",
    "home_name":"Brazil",
    "away_name":"Denmark",
    "home_score":3,
    "away_score":2,
    "home_penalties":null,
    "away_penalties":null,
    "winner":"BRA",
    "home_tactics":null,
    "away_tactics":null,
    "home_possession":null,
    "away_possession":null,
    "attendance":null,
    "stadium":"Stade de la Beaujoire",
    "humidity":null,
    "temperature":null,
    "wind_speed":null,
    "weather":null
  },
  {
    "id_match":"8784",
    "match_number":60,
    "stage":"Quarter-final",
    "group":null,
    "date_utc":"1998-07-04",
    "match_status":0,
    "result_type":1,
    "home_team":"NED",
    "away_team":"ARG",
    "home_name":"Netherlands",
    "away_name":"Argentina",
    "home_score":2,
    "away_score":1,
    "home_penalties":null,
    "away_penalties":null,
    "winner":"NED",
    "home_tactics":null,
    "away_tactics":null,
    "home_possession":null,
    "away_possession":null,
    "attendance":null,
    "stadium":"Stade Vélodrome",
    "humidity":null,
    "temperature":null,
    "wind_speed":null,
    "weather":null
  },
  {
    "id_match":"8783",
    "match_number":59,
    "stage":"Quarter-final",
    "group":null,
    "date_utc":"1998-07-04",
    "match_status":0,
    "result_type":1,
    "home_team":"GER",
    "away_team":"CRO",
    "home_name":"Germany",
    "away_name":"Croatia",
    "home_score":0,
    "away_score":3,
    "home_penalties":null,
    "away_penalties":null,
    "winner":"CRO",
    "home_tactics":null,
    "away_tactics":null,
    "home_possession":null,
    "away_possession":null,
    "attendance":null,
    "stadium":"Stade de Gerland",
    "humidity":null,
    "temperature":null,
    "wind_speed":null,
    "weather":null
  },
  {
    "id_match":"8785",
    "match_number":61,
    "stage":"Semi-final",
    "group":null,
    "date_utc":"1998-07-07",
    "match_status":0,
    "result_type":2,
    "home_team":"BRA",
    "away_team":"NED",
    "home_name":"Brazil",
    "away_name":"Netherlands",
    "home_score":1,
    "away_score":1,
    "home_penalties":4.0,
    "away_penalties":2.0,
    "winner":"BRA",
    "home_tactics":null,
    "away_tactics":null,
    "home_possession":null,
    "away_possession":null,
    "attendance":null,
    "stadium":"Stade Vélodrome",
    "humidity":null,
    "temperature":null,
    "wind_speed":null,
    "weather":null
  },
  {
    "id_match":"8786",
    "match_number":62,
    "stage":"Semi-final",
    "group":null,
    "date_utc":"1998-07-08",
    "match_status":0,
    "result_type":1,
    "home_team":"FRA",
    "away_team":"CRO",
    "home_name":"France",
    "away_name":"Croatia",
    "home_score":2,
    "away_score":1,
    "home_penalties":null,
    "away_penalties":null,
    "winner":"FRA",
    "home_tactics":null,
    "away_tactics":null,
    "home_possession":null,
    "away_possession":null,
    "attendance":null,
    "stadium":"Stade de France",
    "humidity":null,
    "temperature":null,
    "wind_speed":null,
    "weather":null
  },
  {
    "id_match":"8787",
    "match_number":63,
    "stage":"Match for third place",
    "group":null,
    "date_utc":"1998-07-11",
    "match_status":0,
    "result_type":1,
    "home_team":"NED",
    "away_team":"CRO",
    "home_name":"Netherlands",
    "away_name":"Croatia",
    "home_score":1,
    "away_score":2,
    "home_penalties":null,
    "away_penalties":null,
    "winner":"CRO",
    "home_tactics":null,
    "away_tactics":null,
    "home_possession":null,
    "away_possession":null,
    "attendance":null,
    "stadium":"Parc des Princes",
    "humidity":null,
    "temperature":null,
    "wind_speed":null,
    "weather":null
  },
  {
    "id_match":"8788",
    "match_number":64,
    "stage":"Final",
    "group":null,
    "date_utc":"1998-07-12",
    "match_status":0,
    "result_type":1,
    "home_team":"BRA",
    "away_team":"FRA",
    "home_name":"Brazil",
    "away_name":"France",
    "home_score":0,
    "away_score":3,
    "home_penalties":null,
    "away_penalties":null,
    "winner":"FRA",
    "home_tactics":null,
    "away_tactics":null,
    "home_possession":null,
    "away_possession":null,
    "attendance":null,
    "stadium":"Stade de France",
    "humidity":null,
    "temperature":null,
    "wind_speed":null,
    "weather":null
  }
]